{
  "周密晒转账记录": {
    "url": "https://s.weibo.com/weibo?q=%23%E5%91%A8%E5%AF%86%E6%99%92%E8%BD%AC%E8%B4%A6%E8%AE%B0%E5%BD%95%23&t=31&band_rank=1&Refer=top",
    "hot": 2790541
  },
  "李行亮商演遭网友抵制": {
    "url": "https://s.weibo.com/weibo?q=%23%E6%9D%8E%E8%A1%8C%E4%BA%AE%E5%95%86%E6%BC%94%E9%81%AD%E7%BD%91%E5%8F%8B%E6%8A%B5%E5%88%B6%23&t=31&band_rank=1&Refer=top",
    "hot": 1928324
  },
  "双轨 停拍": {
    "url": "https://s.weibo.com/weibo?q=%E5%8F%8C%E8%BD%A8%20%E5%81%9C%E6%8B%8D&t=31&band_rank=1&Refer=top",
    "hot": 1172673
  },
  "艾滋夫妇确诊感染后的第20年": {
    "url": "https://s.weibo.com/weibo?q=%23%E8%89%BE%E6%BB%8B%E5%A4%AB%E5%A6%87%E7%A1%AE%E8%AF%8A%E6%84%9F%E6%9F%93%E5%90%8E%E7%9A%84%E7%AC%AC20%E5%B9%B4%23&t=31&band_rank=2&Refer=top",
    "hot": 841334
  },
  "微观链博会": {
    "url": "https://s.weibo.com/weibo?q=%23%E5%BE%AE%E8%A7%82%E9%93%BE%E5%8D%9A%E4%BC%9A%23&t=31&band_rank=3&Refer=top",
    "hot": 617433
  },
  "黄景瑜孙千 尴尬": {
    "url": "https://s.weibo.com/weibo?q=%E9%BB%84%E6%99%AF%E7%91%9C%E5%AD%99%E5%8D%83%20%E5%B0%B4%E5%B0%AC&t=31&band_rank=4&Refer=top",
    "hot": 606962
  },
  "员工已读不回负责人凌晨爆粗口": {
    "url": "https://s.weibo.com/weibo?q=%23%E5%91%98%E5%B7%A5%E5%B7%B2%E8%AF%BB%E4%B8%8D%E5%9B%9E%E8%B4%9F%E8%B4%A3%E4%BA%BA%E5%87%8C%E6%99%A8%E7%88%86%E7%B2%97%E5%8F%A3%23&t=31&band_rank=2&Refer=top",
    "hot": 594894
  },
  "日本正考虑推进简化中国公民赴日签证手续": {
    "url": "https://s.weibo.com/weibo?q=%23%E6%97%A5%E6%9C%AC%E6%AD%A3%E8%80%83%E8%99%91%E6%8E%A8%E8%BF%9B%E7%AE%80%E5%8C%96%E4%B8%AD%E5%9B%BD%E5%85%AC%E6%B0%91%E8%B5%B4%E6%97%A5%E7%AD%BE%E8%AF%81%E6%89%8B%E7%BB%AD%23&t=31&band_rank=5&Refer=top",
    "hot": 587273
  },
  "中国籍男子承认涂鸦日本靖国神社": {
    "url": "https://s.weibo.com/weibo?q=%23%E4%B8%AD%E5%9B%BD%E7%B1%8D%E7%94%B7%E5%AD%90%E6%89%BF%E8%AE%A4%E6%B6%82%E9%B8%A6%E6%97%A5%E6%9C%AC%E9%9D%96%E5%9B%BD%E7%A5%9E%E7%A4%BE%23&t=31&band_rank=11&Refer=top",
    "hot": 471575
  },
  "恋与制作人大婚": {
    "url": "https://s.weibo.com/weibo?q=%23%E6%81%8B%E4%B8%8E%E5%88%B6%E4%BD%9C%E4%BA%BA%E5%A4%A7%E5%A9%9A%23&t=31&band_rank=6&Refer=top",
    "hot": 466806
  },
  "周密发歌diss周芯竹": {
    "url": "https://s.weibo.com/weibo?q=%E5%91%A8%E5%AF%86%E5%8F%91%E6%AD%8Cdiss%E5%91%A8%E8%8A%AF%E7%AB%B9&t=31&band_rank=7&Refer=top",
    "hot": 454571
  },
  "何以中国弦歌不辍": {
    "url": "https://s.weibo.com/weibo?q=%23%E4%BD%95%E4%BB%A5%E4%B8%AD%E5%9B%BD%E5%BC%A6%E6%AD%8C%E4%B8%8D%E8%BE%8D%23&t=31&band_rank=3&Refer=top",
    "hot": 453069
  },
  "24岁女设计师胃癌晚期问为啥是我": {
    "url": "https://s.weibo.com/weibo?q=%2324%E5%B2%81%E5%A5%B3%E8%AE%BE%E8%AE%A1%E5%B8%88%E8%83%83%E7%99%8C%E6%99%9A%E6%9C%9F%E9%97%AE%E4%B8%BA%E5%95%A5%E6%98%AF%E6%88%91%23&t=31&band_rank=5&Refer=top",
    "hot": 451620
  },
  "四川北川一村民家中遭黑熊袭击": {
    "url": "https://s.weibo.com/weibo?q=%23%E5%9B%9B%E5%B7%9D%E5%8C%97%E5%B7%9D%E4%B8%80%E6%9D%91%E6%B0%91%E5%AE%B6%E4%B8%AD%E9%81%AD%E9%BB%91%E7%86%8A%E8%A2%AD%E5%87%BB%23&t=31&band_rank=10&Refer=top",
    "hot": 411594
  },
  "越南将投入670亿美元修高铁": {
    "url": "https://s.weibo.com/weibo?q=%23%E8%B6%8A%E5%8D%97%E5%B0%86%E6%8A%95%E5%85%A5670%E4%BA%BF%E7%BE%8E%E5%85%83%E4%BF%AE%E9%AB%98%E9%93%81%23&t=31&band_rank=6&Refer=top",
    "hot": 398458
  },
  "玄彬孙艺珍近照": {
    "url": "https://s.weibo.com/weibo?q=%23%E7%8E%84%E5%BD%AC%E5%AD%99%E8%89%BA%E7%8F%8D%E8%BF%91%E7%85%A7%23&t=31&band_rank=7&Refer=top",
    "hot": 398331
  },
  "新疆棉被随便甩不断层": {
    "url": "https://s.weibo.com/weibo?q=%23%E6%96%B0%E7%96%86%E6%A3%89%E8%A2%AB%E9%9A%8F%E4%BE%BF%E7%94%A9%E4%B8%8D%E6%96%AD%E5%B1%82%23&t=31&band_rank=8&Refer=top",
    "hot": 369651
  },
  "分手见人品": {
    "url": "https://s.weibo.com/weibo?q=%E5%88%86%E6%89%8B%E8%A7%81%E4%BA%BA%E5%93%81&t=31&band_rank=11&Refer=top",
    "hot": 365281
  },
  "员工已读不回领导身份不是爆粗口理由": {
    "url": "https://s.weibo.com/weibo?q=%23%E5%91%98%E5%B7%A5%E5%B7%B2%E8%AF%BB%E4%B8%8D%E5%9B%9E%E9%A2%86%E5%AF%BC%E8%BA%AB%E4%BB%BD%E4%B8%8D%E6%98%AF%E7%88%86%E7%B2%97%E5%8F%A3%E7%90%86%E7%94%B1%23&t=31&band_rank=9&Refer=top",
    "hot": 358930
  },
  "gidle全员续约": {
    "url": "https://s.weibo.com/weibo?q=%23gidle%E5%85%A8%E5%91%98%E7%BB%AD%E7%BA%A6%23&t=31&band_rank=12&Refer=top",
    "hot": 354736
  },
  "易烊千玺小网站发了粉丝的声音": {
    "url": "https://s.weibo.com/weibo?q=%23%E6%98%93%E7%83%8A%E5%8D%83%E7%8E%BA%E5%B0%8F%E7%BD%91%E7%AB%99%E5%8F%91%E4%BA%86%E7%B2%89%E4%B8%9D%E7%9A%84%E5%A3%B0%E9%9F%B3%23&t=31&band_rank=13&Refer=top",
    "hot": 319888
  },
  "一句但悲不见九州同哭倒一片理科生": {
    "url": "https://s.weibo.com/weibo?q=%23%E4%B8%80%E5%8F%A5%E4%BD%86%E6%82%B2%E4%B8%8D%E8%A7%81%E4%B9%9D%E5%B7%9E%E5%90%8C%E5%93%AD%E5%80%92%E4%B8%80%E7%89%87%E7%90%86%E7%A7%91%E7%94%9F%23&t=31&band_rank=4&Refer=top",
    "hot": 304479
  },
  "贾斯汀比伯一家三口合照": {
    "url": "https://s.weibo.com/weibo?q=%23%E8%B4%BE%E6%96%AF%E6%B1%80%E6%AF%94%E4%BC%AF%E4%B8%80%E5%AE%B6%E4%B8%89%E5%8F%A3%E5%90%88%E7%85%A7%23&t=31&band_rank=10&Refer=top",
    "hot": 291619
  },
  "linglingkwong": {
    "url": "https://s.weibo.com/weibo?q=%23linglingkwong%23&t=31&band_rank=11&Refer=top",
    "hot": 291488
  },
  "吴谨言12月暂无公开行程": {
    "url": "https://s.weibo.com/weibo?q=%23%E5%90%B4%E8%B0%A8%E8%A8%8012%E6%9C%88%E6%9A%82%E6%97%A0%E5%85%AC%E5%BC%80%E8%A1%8C%E7%A8%8B%23&t=31&band_rank=12&Refer=top",
    "hot": 290751
  },
  "张小斐 喜欢肢体接触是吧": {
    "url": "https://s.weibo.com/weibo?q=%E5%BC%A0%E5%B0%8F%E6%96%90%20%E5%96%9C%E6%AC%A2%E8%82%A2%E4%BD%93%E6%8E%A5%E8%A7%A6%E6%98%AF%E5%90%A7&t=31&band_rank=14&Refer=top",
    "hot": 284902
  },
  "中企参展人员遭美国大规模拒签": {
    "url": "https://s.weibo.com/weibo?q=%23%E4%B8%AD%E4%BC%81%E5%8F%82%E5%B1%95%E4%BA%BA%E5%91%98%E9%81%AD%E7%BE%8E%E5%9B%BD%E5%A4%A7%E8%A7%84%E6%A8%A1%E6%8B%92%E7%AD%BE%23&t=31&band_rank=5&Refer=top",
    "hot": 280369
  },
  "鹿晗 别逼我把韬叫上来": {
    "url": "https://s.weibo.com/weibo?q=%E9%B9%BF%E6%99%97%20%E5%88%AB%E9%80%BC%E6%88%91%E6%8A%8A%E9%9F%AC%E5%8F%AB%E4%B8%8A%E6%9D%A5&t=31&band_rank=6&Refer=top",
    "hot": 279827
  },
  "陈赫回应鹿晗直播": {
    "url": "https://s.weibo.com/weibo?q=%23%E9%99%88%E8%B5%AB%E5%9B%9E%E5%BA%94%E9%B9%BF%E6%99%97%E7%9B%B4%E6%92%AD%23&t=31&band_rank=7&Refer=top",
    "hot": 278052
  },
  "金莎焉栩嘉逛街被偶遇": {
    "url": "https://s.weibo.com/weibo?q=%E9%87%91%E8%8E%8E%E7%84%89%E6%A0%A9%E5%98%89%E9%80%9B%E8%A1%97%E8%A2%AB%E5%81%B6%E9%81%87&t=31&band_rank=8&Refer=top",
    "hot": 275838
  },
  "金智秀连续三年获世首美": {
    "url": "https://s.weibo.com/weibo?q=%23%E9%87%91%E6%99%BA%E7%A7%80%E8%BF%9E%E7%BB%AD%E4%B8%89%E5%B9%B4%E8%8E%B7%E4%B8%96%E9%A6%96%E7%BE%8E%23&t=31&band_rank=13&Refer=top",
    "hot": 274685
  },
  "王楚钦混团抽签台下画画": {
    "url": "https://s.weibo.com/weibo?q=%23%E7%8E%8B%E6%A5%9A%E9%92%A6%E6%B7%B7%E5%9B%A2%E6%8A%BD%E7%AD%BE%E5%8F%B0%E4%B8%8B%E7%94%BB%E7%94%BB%23&t=31&band_rank=9&Refer=top",
    "hot": 271587
  },
  "12月十二星座注意事项": {
    "url": "https://s.weibo.com/weibo?q=%2312%E6%9C%88%E5%8D%81%E4%BA%8C%E6%98%9F%E5%BA%A7%E6%B3%A8%E6%84%8F%E4%BA%8B%E9%A1%B9%23&t=31&band_rank=15&Refer=top",
    "hot": 268488
  },
  "永夜星河逆跌": {
    "url": "https://s.weibo.com/weibo?q=%E6%B0%B8%E5%A4%9C%E6%98%9F%E6%B2%B3%E9%80%86%E8%B7%8C&t=31&band_rank=16&Refer=top",
    "hot": 265677
  },
  "300万投资变成了6万斤网络牛肉": {
    "url": "https://s.weibo.com/weibo?q=%23300%E4%B8%87%E6%8A%95%E8%B5%84%E5%8F%98%E6%88%90%E4%BA%866%E4%B8%87%E6%96%A4%E7%BD%91%E7%BB%9C%E7%89%9B%E8%82%89%23&t=31&band_rank=17&Refer=top",
    "hot": 256173
  },
  "当地交警回应45岁医生出车祸去世": {
    "url": "https://s.weibo.com/weibo?q=%23%E5%BD%93%E5%9C%B0%E4%BA%A4%E8%AD%A6%E5%9B%9E%E5%BA%9445%E5%B2%81%E5%8C%BB%E7%94%9F%E5%87%BA%E8%BD%A6%E7%A5%B8%E5%8E%BB%E4%B8%96%23&t=31&band_rank=18&Refer=top",
    "hot": 256078
  },
  "百名会员刚办完卡洗浴店一夜关门": {
    "url": "https://s.weibo.com/weibo?q=%23%E7%99%BE%E5%90%8D%E4%BC%9A%E5%91%98%E5%88%9A%E5%8A%9E%E5%AE%8C%E5%8D%A1%E6%B4%97%E6%B5%B4%E5%BA%97%E4%B8%80%E5%A4%9C%E5%85%B3%E9%97%A8%23&t=31&band_rank=19&Refer=top",
    "hot": 256040
  },
  "六千八买两个二手LV包被鉴定为假": {
    "url": "https://s.weibo.com/weibo?q=%23%E5%85%AD%E5%8D%83%E5%85%AB%E4%B9%B0%E4%B8%A4%E4%B8%AA%E4%BA%8C%E6%89%8BLV%E5%8C%85%E8%A2%AB%E9%89%B4%E5%AE%9A%E4%B8%BA%E5%81%87%23&t=31&band_rank=20&Refer=top",
    "hot": 255853
  },
  "范丞丞希望粉丝对工作室嘴下留情": {
    "url": "https://s.weibo.com/weibo?q=%23%E8%8C%83%E4%B8%9E%E4%B8%9E%E5%B8%8C%E6%9C%9B%E7%B2%89%E4%B8%9D%E5%AF%B9%E5%B7%A5%E4%BD%9C%E5%AE%A4%E5%98%B4%E4%B8%8B%E7%95%99%E6%83%85%23&t=31&band_rank=21&Refer=top",
    "hot": 255715
  },
  "结婚1年多不孕夫妻变姐妹": {
    "url": "https://s.weibo.com/weibo?q=%23%E7%BB%93%E5%A9%9A1%E5%B9%B4%E5%A4%9A%E4%B8%8D%E5%AD%95%E5%A4%AB%E5%A6%BB%E5%8F%98%E5%A7%90%E5%A6%B9%23&t=31&band_rank=22&Refer=top",
    "hot": 255606
  },
  "新床单晒了一次变微信聊天背景图了": {
    "url": "https://s.weibo.com/weibo?q=%23%E6%96%B0%E5%BA%8A%E5%8D%95%E6%99%92%E4%BA%86%E4%B8%80%E6%AC%A1%E5%8F%98%E5%BE%AE%E4%BF%A1%E8%81%8A%E5%A4%A9%E8%83%8C%E6%99%AF%E5%9B%BE%E4%BA%86%23&t=31&band_rank=23&Refer=top",
    "hot": 255493
  },
  "内娱第一个能保护黄景瑜的男人": {
    "url": "https://s.weibo.com/weibo?q=%E5%86%85%E5%A8%B1%E7%AC%AC%E4%B8%80%E4%B8%AA%E8%83%BD%E4%BF%9D%E6%8A%A4%E9%BB%84%E6%99%AF%E7%91%9C%E7%9A%84%E7%94%B7%E4%BA%BA&t=31&band_rank=24&Refer=top",
    "hot": 255412
  },
  "Tarzan加入AL": {
    "url": "https://s.weibo.com/weibo?q=%23Tarzan%E5%8A%A0%E5%85%A5AL%23&t=31&band_rank=25&Refer=top",
    "hot": 255275
  },
  "好东西": {
    "url": "https://s.weibo.com/weibo?q=%E5%A5%BD%E4%B8%9C%E8%A5%BF&t=31&band_rank=26&Refer=top",
    "hot": 255236
  },
  "免签朋友圈一个月两次扩容": {
    "url": "https://s.weibo.com/weibo?q=%23%E5%85%8D%E7%AD%BE%E6%9C%8B%E5%8F%8B%E5%9C%88%E4%B8%80%E4%B8%AA%E6%9C%88%E4%B8%A4%E6%AC%A1%E6%89%A9%E5%AE%B9%23&t=31&band_rank=10&Refer=top",
    "hot": 248086
  },
  "aespa全员黑裙": {
    "url": "https://s.weibo.com/weibo?q=%23aespa%E5%85%A8%E5%91%98%E9%BB%91%E8%A3%99%23&t=31&band_rank=12&Refer=top",
    "hot": 233929
  },
  "沈梦瑶与丝芭解约成功": {
    "url": "https://s.weibo.com/weibo?q=%23%E6%B2%88%E6%A2%A6%E7%91%B6%E4%B8%8E%E4%B8%9D%E8%8A%AD%E8%A7%A3%E7%BA%A6%E6%88%90%E5%8A%9F%23&t=31&band_rank=13&Refer=top",
    "hot": 228268
  },
  "人民网评优衣库事件": {
    "url": "https://s.weibo.com/weibo?q=%23%E4%BA%BA%E6%B0%91%E7%BD%91%E8%AF%84%E4%BC%98%E8%A1%A3%E5%BA%93%E4%BA%8B%E4%BB%B6%23&t=31&band_rank=14&Refer=top",
    "hot": 228091
  },
  "乔任梁父亲曾在儿子墓地见到造谣者": {
    "url": "https://s.weibo.com/weibo?q=%23%E4%B9%94%E4%BB%BB%E6%A2%81%E7%88%B6%E4%BA%B2%E6%9B%BE%E5%9C%A8%E5%84%BF%E5%AD%90%E5%A2%93%E5%9C%B0%E8%A7%81%E5%88%B0%E9%80%A0%E8%B0%A3%E8%80%85%23&t=31&band_rank=14&Refer=top",
    "hot": 225483
  },
  "信阳一副镇长被指开套牌车还打人": {
    "url": "https://s.weibo.com/weibo?q=%23%E4%BF%A1%E9%98%B3%E4%B8%80%E5%89%AF%E9%95%87%E9%95%BF%E8%A2%AB%E6%8C%87%E5%BC%80%E5%A5%97%E7%89%8C%E8%BD%A6%E8%BF%98%E6%89%93%E4%BA%BA%23&t=31&band_rank=15&Refer=top",
    "hot": 223761
  },
  "安徽一学校食堂俩员工吵架打翻饭菜": {
    "url": "https://s.weibo.com/weibo?q=%23%E5%AE%89%E5%BE%BD%E4%B8%80%E5%AD%A6%E6%A0%A1%E9%A3%9F%E5%A0%82%E4%BF%A9%E5%91%98%E5%B7%A5%E5%90%B5%E6%9E%B6%E6%89%93%E7%BF%BB%E9%A5%AD%E8%8F%9C%23&t=31&band_rank=16&Refer=top",
    "hot": 221131
  },
  "日本超330家自来水企业检出永久性化学物质": {
    "url": "https://s.weibo.com/weibo?q=%23%E6%97%A5%E6%9C%AC%E8%B6%85330%E5%AE%B6%E8%87%AA%E6%9D%A5%E6%B0%B4%E4%BC%81%E4%B8%9A%E6%A3%80%E5%87%BA%E6%B0%B8%E4%B9%85%E6%80%A7%E5%8C%96%E5%AD%A6%E7%89%A9%E8%B4%A8%23&t=31&band_rank=17&Refer=top",
    "hot": 218360
  },
  "韩剧现在拨打的电话": {
    "url": "https://s.weibo.com/weibo?q=%23%E9%9F%A9%E5%89%A7%E7%8E%B0%E5%9C%A8%E6%8B%A8%E6%89%93%E7%9A%84%E7%94%B5%E8%AF%9D%23&t=31&band_rank=27&Refer=top",
    "hot": 218264
  },
  "生酮饮食饿死癌细胞是误导": {
    "url": "https://s.weibo.com/weibo?q=%23%E7%94%9F%E9%85%AE%E9%A5%AE%E9%A3%9F%E9%A5%BF%E6%AD%BB%E7%99%8C%E7%BB%86%E8%83%9E%E6%98%AF%E8%AF%AF%E5%AF%BC%23&t=31&band_rank=15&Refer=top",
    "hot": 216130
  },
  "贺峻霖在张蔷头发里找张蔷": {
    "url": "https://s.weibo.com/weibo?q=%23%E8%B4%BA%E5%B3%BB%E9%9C%96%E5%9C%A8%E5%BC%A0%E8%94%B7%E5%A4%B4%E5%8F%91%E9%87%8C%E6%89%BE%E5%BC%A0%E8%94%B7%23&t=31&band_rank=18&Refer=top",
    "hot": 216089
  },
  "超10万乌军士兵被指控当逃兵": {
    "url": "https://s.weibo.com/weibo?q=%23%E8%B6%8510%E4%B8%87%E4%B9%8C%E5%86%9B%E5%A3%AB%E5%85%B5%E8%A2%AB%E6%8C%87%E6%8E%A7%E5%BD%93%E9%80%83%E5%85%B5%23&t=31&band_rank=19&Refer=top",
    "hot": 215851
  },
  "4人靠云养牛骗了5个亿": {
    "url": "https://s.weibo.com/weibo?q=%234%E4%BA%BA%E9%9D%A0%E4%BA%91%E5%85%BB%E7%89%9B%E9%AA%97%E4%BA%865%E4%B8%AA%E4%BA%BF%23&t=31&band_rank=20&Refer=top",
    "hot": 215134
  },
  "年轻人得胃癌跟吃外卖有关系吗": {
    "url": "https://s.weibo.com/weibo?q=%23%E5%B9%B4%E8%BD%BB%E4%BA%BA%E5%BE%97%E8%83%83%E7%99%8C%E8%B7%9F%E5%90%83%E5%A4%96%E5%8D%96%E6%9C%89%E5%85%B3%E7%B3%BB%E5%90%97%23&t=31&band_rank=21&Refer=top",
    "hot": 214944
  },
  "戚薇直播": {
    "url": "https://s.weibo.com/weibo?q=%E6%88%9A%E8%96%87%E7%9B%B4%E6%92%AD&t=31&band_rank=22&Refer=top",
    "hot": 214215
  },
  "周密": {
    "url": "https://s.weibo.com/weibo?q=%E5%91%A8%E5%AF%86&t=31&band_rank=28&Refer=top",
    "hot": 213840
  },
  "我是刑警生子下线": {
    "url": "https://s.weibo.com/weibo?q=%E6%88%91%E6%98%AF%E5%88%91%E8%AD%A6%E7%94%9F%E5%AD%90%E4%B8%8B%E7%BA%BF&t=31&band_rank=24&Refer=top",
    "hot": 213427
  },
  "2024军团杯": {
    "url": "https://s.weibo.com/weibo?q=2024%E5%86%9B%E5%9B%A2%E6%9D%AF&t=31&band_rank=25&Refer=top",
    "hot": 212915
  },
  "怀上九胞胎女子减7胎后出院": {
    "url": "https://s.weibo.com/weibo?q=%23%E6%80%80%E4%B8%8A%E4%B9%9D%E8%83%9E%E8%83%8E%E5%A5%B3%E5%AD%90%E5%87%8F7%E8%83%8E%E5%90%8E%E5%87%BA%E9%99%A2%23&t=31&band_rank=26&Refer=top",
    "hot": 212423
  },
  "芒果男艺人芭莎没站C位": {
    "url": "https://s.weibo.com/weibo?q=%E8%8A%92%E6%9E%9C%E7%94%B7%E8%89%BA%E4%BA%BA%E8%8A%AD%E8%8E%8E%E6%B2%A1%E7%AB%99C%E4%BD%8D&t=31&band_rank=27&Refer=top",
    "hot": 211503
  },
  "杜甫写诗像在发朋友圈": {
    "url": "https://s.weibo.com/weibo?q=%23%E6%9D%9C%E7%94%AB%E5%86%99%E8%AF%97%E5%83%8F%E5%9C%A8%E5%8F%91%E6%9C%8B%E5%8F%8B%E5%9C%88%23&t=31&band_rank=28&Refer=top",
    "hot": 210982
  },
  "沧元图2定档": {
    "url": "https://s.weibo.com/weibo?q=%23%E6%B2%A7%E5%85%83%E5%9B%BE2%E5%AE%9A%E6%A1%A3%23&t=31&band_rank=29&Refer=top",
    "hot": 210751
  },
  "男子打伞骑车15cm竹子插入眼睛": {
    "url": "https://s.weibo.com/weibo?q=%23%E7%94%B7%E5%AD%90%E6%89%93%E4%BC%9E%E9%AA%91%E8%BD%A615cm%E7%AB%B9%E5%AD%90%E6%8F%92%E5%85%A5%E7%9C%BC%E7%9D%9B%23&t=31&band_rank=30&Refer=top",
    "hot": 210343
  },
  "微信朋友圈显示未能点赞": {
    "url": "https://s.weibo.com/weibo?q=%23%E5%BE%AE%E4%BF%A1%E6%9C%8B%E5%8F%8B%E5%9C%88%E6%98%BE%E7%A4%BA%E6%9C%AA%E8%83%BD%E7%82%B9%E8%B5%9E%23&t=31&band_rank=32&Refer=top",
    "hot": 209941
  },
  "合肥LV柜姐离职后开始卖货": {
    "url": "https://s.weibo.com/weibo?q=%23%E5%90%88%E8%82%A5LV%E6%9F%9C%E5%A7%90%E7%A6%BB%E8%81%8C%E5%90%8E%E5%BC%80%E5%A7%8B%E5%8D%96%E8%B4%A7%23&t=31&band_rank=16&Refer=top",
    "hot": 209366
  },
  "向佐地位又要降了": {
    "url": "https://s.weibo.com/weibo?q=%23%E5%90%91%E4%BD%90%E5%9C%B0%E4%BD%8D%E5%8F%88%E8%A6%81%E9%99%8D%E4%BA%86%23&t=31&band_rank=17&Refer=top",
    "hot": 205470
  },
  "心理专家谈好东西中小孩姐的选择": {
    "url": "https://s.weibo.com/weibo?q=%23%E5%BF%83%E7%90%86%E4%B8%93%E5%AE%B6%E8%B0%88%E5%A5%BD%E4%B8%9C%E8%A5%BF%E4%B8%AD%E5%B0%8F%E5%AD%A9%E5%A7%90%E7%9A%84%E9%80%89%E6%8B%A9%23&t=31&band_rank=29&Refer=top",
    "hot": 203505
  },
  "诗情画奕": {
    "url": "https://s.weibo.com/weibo?q=%E8%AF%97%E6%83%85%E7%94%BB%E5%A5%95&t=31&band_rank=30&Refer=top",
    "hot": 202614
  },
  "严浩翔新剧被霸凌路透": {
    "url": "https://s.weibo.com/weibo?q=%23%E4%B8%A5%E6%B5%A9%E7%BF%94%E6%96%B0%E5%89%A7%E8%A2%AB%E9%9C%B8%E5%87%8C%E8%B7%AF%E9%80%8F%23&t=31&band_rank=31&Refer=top",
    "hot": 202434
  },
  "骄阳似我": {
    "url": "https://s.weibo.com/weibo?q=%E9%AA%84%E9%98%B3%E4%BC%BC%E6%88%91&t=31&band_rank=32&Refer=top",
    "hot": 202335
  },
  "赵露思去看凤凰传奇演唱会了": {
    "url": "https://s.weibo.com/weibo?q=%23%E8%B5%B5%E9%9C%B2%E6%80%9D%E5%8E%BB%E7%9C%8B%E5%87%A4%E5%87%B0%E4%BC%A0%E5%A5%87%E6%BC%94%E5%94%B1%E4%BC%9A%E4%BA%86%23&t=31&band_rank=33&Refer=top",
    "hot": 196167
  },
  "我是刑警 敢拍": {
    "url": "https://s.weibo.com/weibo?q=%E6%88%91%E6%98%AF%E5%88%91%E8%AD%A6%20%E6%95%A2%E6%8B%8D&t=31&band_rank=32&Refer=top",
    "hot": 195179
  },
  "杭州首套房贷利率上调至3.1%": {
    "url": "https://s.weibo.com/weibo?q=%23%E6%9D%AD%E5%B7%9E%E9%A6%96%E5%A5%97%E6%88%BF%E8%B4%B7%E5%88%A9%E7%8E%87%E4%B8%8A%E8%B0%83%E8%87%B33.1%25%23&t=31&band_rank=33&Refer=top",
    "hot": 193830
  },
  "DOU5对战WBG": {
    "url": "https://s.weibo.com/weibo?q=%23DOU5%E5%AF%B9%E6%88%98WBG%23&t=31&band_rank=34&Refer=top",
    "hot": 192044
  },
  "考公上岸后的体制内生活是什么样": {
    "url": "https://s.weibo.com/weibo?q=%23%E8%80%83%E5%85%AC%E4%B8%8A%E5%B2%B8%E5%90%8E%E7%9A%84%E4%BD%93%E5%88%B6%E5%86%85%E7%94%9F%E6%B4%BB%E6%98%AF%E4%BB%80%E4%B9%88%E6%A0%B7%23&t=31&band_rank=18&Refer=top",
    "hot": 189110
  },
  "国考人数创新高平均录取比86比1": {
    "url": "https://s.weibo.com/weibo?q=%23%E5%9B%BD%E8%80%83%E4%BA%BA%E6%95%B0%E5%88%9B%E6%96%B0%E9%AB%98%E5%B9%B3%E5%9D%87%E5%BD%95%E5%8F%96%E6%AF%9486%E6%AF%941%23&t=31&band_rank=19&Refer=top",
    "hot": 188425
  },
  "郭艾伦32分": {
    "url": "https://s.weibo.com/weibo?q=%E9%83%AD%E8%89%BE%E4%BC%A632%E5%88%86&t=31&band_rank=34&Refer=top",
    "hot": 187703
  },
  "黄景瑜庆生随拍": {
    "url": "https://s.weibo.com/weibo?q=%23%E9%BB%84%E6%99%AF%E7%91%9C%E5%BA%86%E7%94%9F%E9%9A%8F%E6%8B%8D%23&t=31&band_rank=20&Refer=top",
    "hot": 186342
  },
  "丁禹兮黑白森林反差感": {
    "url": "https://s.weibo.com/weibo?q=%E4%B8%81%E7%A6%B9%E5%85%AE%E9%BB%91%E7%99%BD%E6%A3%AE%E6%9E%97%E5%8F%8D%E5%B7%AE%E6%84%9F&t=31&band_rank=35&Refer=top",
    "hot": 185217
  },
  "结婚3年流产2次竟是老公精子碎了": {
    "url": "https://s.weibo.com/weibo?q=%23%E7%BB%93%E5%A9%9A3%E5%B9%B4%E6%B5%81%E4%BA%A72%E6%AC%A1%E7%AB%9F%E6%98%AF%E8%80%81%E5%85%AC%E7%B2%BE%E5%AD%90%E7%A2%8E%E4%BA%86%23&t=31&band_rank=21&Refer=top",
    "hot": 182411
  },
  "孟子义李昀锐好嗑": {
    "url": "https://s.weibo.com/weibo?q=%E5%AD%9F%E5%AD%90%E4%B9%89%E6%9D%8E%E6%98%80%E9%94%90%E5%A5%BD%E5%97%91&t=31&band_rank=36&Refer=top",
    "hot": 180422
  },
  "一路繁花直播": {
    "url": "https://s.weibo.com/weibo?q=%23%E4%B8%80%E8%B7%AF%E7%B9%81%E8%8A%B1%E7%9B%B4%E6%92%AD%23&t=31&band_rank=36&Refer=top",
    "hot": 180417
  },
  "时代少年团元梦峡谷首秀": {
    "url": "https://s.weibo.com/weibo?q=%23%E6%97%B6%E4%BB%A3%E5%B0%91%E5%B9%B4%E5%9B%A2%E5%85%83%E6%A2%A6%E5%B3%A1%E8%B0%B7%E9%A6%96%E7%A7%80%23&t=31&band_rank=37&Refer=top",
    "hot": 179973
  },
  "麦琳怒怼杨子": {
    "url": "https://s.weibo.com/weibo?q=%23%E9%BA%A6%E7%90%B3%E6%80%92%E6%80%BC%E6%9D%A8%E5%AD%90%23&t=31&band_rank=22&Refer=top",
    "hot": 178918
  },
  "胃病向胃癌转变的5个信号": {
    "url": "https://s.weibo.com/weibo?q=%23%E8%83%83%E7%97%85%E5%90%91%E8%83%83%E7%99%8C%E8%BD%AC%E5%8F%98%E7%9A%845%E4%B8%AA%E4%BF%A1%E5%8F%B7%23&t=31&band_rank=37&Refer=top",
    "hot": 178309
  },
  "肖战工作室": {
    "url": "https://s.weibo.com/weibo?q=%E8%82%96%E6%88%98%E5%B7%A5%E4%BD%9C%E5%AE%A4&t=31&band_rank=23&Refer=top",
    "hot": 178295
  },
  "男子确诊肺癌医生一根针冻死癌细胞": {
    "url": "https://s.weibo.com/weibo?q=%23%E7%94%B7%E5%AD%90%E7%A1%AE%E8%AF%8A%E8%82%BA%E7%99%8C%E5%8C%BB%E7%94%9F%E4%B8%80%E6%A0%B9%E9%92%88%E5%86%BB%E6%AD%BB%E7%99%8C%E7%BB%86%E8%83%9E%23&t=31&band_rank=24&Refer=top",
    "hot": 175628
  },
  "国考公安": {
    "url": "https://s.weibo.com/weibo?q=%E5%9B%BD%E8%80%83%E5%85%AC%E5%AE%89&t=31&band_rank=25&Refer=top",
    "hot": 173145
  },
  "MMA红毯": {
    "url": "https://s.weibo.com/weibo?q=MMA%E7%BA%A2%E6%AF%AF&t=31&band_rank=27&Refer=top",
    "hot": 172926
  },
  "留几手让葛夕打过胎": {
    "url": "https://s.weibo.com/weibo?q=%23%E7%95%99%E5%87%A0%E6%89%8B%E8%AE%A9%E8%91%9B%E5%A4%95%E6%89%93%E8%BF%87%E8%83%8E%23&t=31&band_rank=26&Refer=top",
    "hot": 169235
  },
  "IVE最佳MV": {
    "url": "https://s.weibo.com/weibo?q=%23IVE%E6%9C%80%E4%BD%B3MV%23&t=31&band_rank=29&Refer=top",
    "hot": 161532
  },
  "张元英开场": {
    "url": "https://s.weibo.com/weibo?q=%23%E5%BC%A0%E5%85%83%E8%8B%B1%E5%BC%80%E5%9C%BA%23&t=31&band_rank=30&Refer=top",
    "hot": 160704
  },
  "aespa获最佳女团": {
    "url": "https://s.weibo.com/weibo?q=%23aespa%E8%8E%B7%E6%9C%80%E4%BD%B3%E5%A5%B3%E5%9B%A2%23&t=31&band_rank=40&Refer=top",
    "hot": 158656
  },
  "元梦之星": {
    "url": "https://s.weibo.com/weibo?q=%E5%85%83%E6%A2%A6%E4%B9%8B%E6%98%9F&t=31&band_rank=31&Refer=top",
    "hot": 158458
  },
  "高泽宇丸子官宣领证": {
    "url": "https://s.weibo.com/weibo?q=%23%E9%AB%98%E6%B3%BD%E5%AE%87%E4%B8%B8%E5%AD%90%E5%AE%98%E5%AE%A3%E9%A2%86%E8%AF%81%23&t=31&band_rank=41&Refer=top",
    "hot": 156525
  },
  "张元英和男伴舞双人芭蕾": {
    "url": "https://s.weibo.com/weibo?q=%23%E5%BC%A0%E5%85%83%E8%8B%B1%E5%92%8C%E7%94%B7%E4%BC%B4%E8%88%9E%E5%8F%8C%E4%BA%BA%E8%8A%AD%E8%95%BE%23&t=31&band_rank=40&Refer=top",
    "hot": 154289
  },
  "韩网友抵制韩国电影": {
    "url": "https://s.weibo.com/weibo?q=%23%E9%9F%A9%E7%BD%91%E5%8F%8B%E6%8A%B5%E5%88%B6%E9%9F%A9%E5%9B%BD%E7%94%B5%E5%BD%B1%23&t=31&band_rank=33&Refer=top",
    "hot": 151519
  },
  "IVE红毯生图": {
    "url": "https://s.weibo.com/weibo?q=IVE%E7%BA%A2%E6%AF%AF%E7%94%9F%E5%9B%BE&t=31&band_rank=34&Refer=top",
    "hot": 151412
  },
  "MMA直播": {
    "url": "https://s.weibo.com/weibo?q=MMA%E7%9B%B4%E6%92%AD&t=31&band_rank=35&Refer=top",
    "hot": 150306
  },
  "肖战 攻玉": {
    "url": "https://s.weibo.com/weibo?q=%E8%82%96%E6%88%98%20%E6%94%BB%E7%8E%89&t=31&band_rank=41&Refer=top",
    "hot": 147832
  },
  "香奈儿15年后中国首秀": {
    "url": "https://s.weibo.com/weibo?q=%E9%A6%99%E5%A5%88%E5%84%BF15%E5%B9%B4%E5%90%8E%E4%B8%AD%E5%9B%BD%E9%A6%96%E7%A7%80&t=31&band_rank=36&Refer=top",
    "hot": 144550
  },
  "已经开始审判葛夕闺蜜了": {
    "url": "https://s.weibo.com/weibo?q=%23%E5%B7%B2%E7%BB%8F%E5%BC%80%E5%A7%8B%E5%AE%A1%E5%88%A4%E8%91%9B%E5%A4%95%E9%97%BA%E8%9C%9C%E4%BA%86%23&t=31&band_rank=37&Refer=top",
    "hot": 144530
  },
  "iG官宣重组": {
    "url": "https://s.weibo.com/weibo?q=%23iG%E5%AE%98%E5%AE%A3%E9%87%8D%E7%BB%84%23&t=31&band_rank=38&Refer=top",
    "hot": 144526
  },
  "我是刑警": {
    "url": "https://s.weibo.com/weibo?q=%E6%88%91%E6%98%AF%E5%88%91%E8%AD%A6&t=31&band_rank=42&Refer=top",
    "hot": 144434
  },
  "朱鹮雾中缓缓降落如画中仙鸟": {
    "url": "https://s.weibo.com/weibo?q=%23%E6%9C%B1%E9%B9%AE%E9%9B%BE%E4%B8%AD%E7%BC%93%E7%BC%93%E9%99%8D%E8%90%BD%E5%A6%82%E7%94%BB%E4%B8%AD%E4%BB%99%E9%B8%9F%23&t=31&band_rank=43&Refer=top",
    "hot": 143013
  },
  "aespa横扫MMA三项大赏": {
    "url": "https://s.weibo.com/weibo?q=%23aespa%E6%A8%AA%E6%89%ABMMA%E4%B8%89%E9%A1%B9%E5%A4%A7%E8%B5%8F%23&t=31&band_rank=43&Refer=top",
    "hot": 142227
  },
  "突然发现考公的人越来越多": {
    "url": "https://s.weibo.com/weibo?q=%23%E7%AA%81%E7%84%B6%E5%8F%91%E7%8E%B0%E8%80%83%E5%85%AC%E7%9A%84%E4%BA%BA%E8%B6%8A%E6%9D%A5%E8%B6%8A%E5%A4%9A%23&t=31&band_rank=44&Refer=top",
    "hot": 141476
  },
  "哈圈": {
    "url": "https://s.weibo.com/weibo?q=%E5%93%88%E5%9C%88&t=31&band_rank=45&Refer=top",
    "hot": 140839
  },
  "女子被2大型犬撕咬司机鸣笛驱赶": {
    "url": "https://s.weibo.com/weibo?q=%23%E5%A5%B3%E5%AD%90%E8%A2%AB2%E5%A4%A7%E5%9E%8B%E7%8A%AC%E6%92%95%E5%92%AC%E5%8F%B8%E6%9C%BA%E9%B8%A3%E7%AC%9B%E9%A9%B1%E8%B5%B6%23&t=31&band_rank=39&Refer=top",
    "hot": 140763
  },
  "法医秦明给我是刑警划重点": {
    "url": "https://s.weibo.com/weibo?q=%E6%B3%95%E5%8C%BB%E7%A7%A6%E6%98%8E%E7%BB%99%E6%88%91%E6%98%AF%E5%88%91%E8%AD%A6%E5%88%92%E9%87%8D%E7%82%B9&t=31&band_rank=44&Refer=top",
    "hot": 140144
  },
  "27岁上海交大博导让大家别焦虑": {
    "url": "https://s.weibo.com/weibo?q=%2327%E5%B2%81%E4%B8%8A%E6%B5%B7%E4%BA%A4%E5%A4%A7%E5%8D%9A%E5%AF%BC%E8%AE%A9%E5%A4%A7%E5%AE%B6%E5%88%AB%E7%84%A6%E8%99%91%23&t=31&band_rank=46&Refer=top",
    "hot": 140091
  },
  "爱情里下意识的举动不会骗人": {
    "url": "https://s.weibo.com/weibo?q=%E7%88%B1%E6%83%85%E9%87%8C%E4%B8%8B%E6%84%8F%E8%AF%86%E7%9A%84%E4%B8%BE%E5%8A%A8%E4%B8%8D%E4%BC%9A%E9%AA%97%E4%BA%BA&t=31&band_rank=46&Refer=top",
    "hot": 139538
  },
  "杜甫是唐代纪录片导演吧": {
    "url": "https://s.weibo.com/weibo?q=%23%E6%9D%9C%E7%94%AB%E6%98%AF%E5%94%90%E4%BB%A3%E7%BA%AA%E5%BD%95%E7%89%87%E5%AF%BC%E6%BC%94%E5%90%A7%23&t=31&band_rank=47&Refer=top",
    "hot": 139436
  },
  "郑雨盛道歉后李惠利的表情": {
    "url": "https://s.weibo.com/weibo?q=%23%E9%83%91%E9%9B%A8%E7%9B%9B%E9%81%93%E6%AD%89%E5%90%8E%E6%9D%8E%E6%83%A0%E5%88%A9%E7%9A%84%E8%A1%A8%E6%83%85%23&t=31&band_rank=40&Refer=top",
    "hot": 137848
  },
  "炕烧塌了为什么东北人开心": {
    "url": "https://s.weibo.com/weibo?q=%23%E7%82%95%E7%83%A7%E5%A1%8C%E4%BA%86%E4%B8%BA%E4%BB%80%E4%B9%88%E4%B8%9C%E5%8C%97%E4%BA%BA%E5%BC%80%E5%BF%83%23&t=31&band_rank=41&Refer=top",
    "hot": 137571
  },
  "只有师范生才懂她有多强": {
    "url": "https://s.weibo.com/weibo?q=%E5%8F%AA%E6%9C%89%E5%B8%88%E8%8C%83%E7%94%9F%E6%89%8D%E6%87%82%E5%A5%B9%E6%9C%89%E5%A4%9A%E5%BC%BA&t=31&band_rank=48&Refer=top",
    "hot": 137178
  },
  "女子5年剖4胎宣布封肚": {
    "url": "https://s.weibo.com/weibo?q=%23%E5%A5%B3%E5%AD%905%E5%B9%B4%E5%89%964%E8%83%8E%E5%AE%A3%E5%B8%83%E5%B0%81%E8%82%9A%23&t=31&band_rank=50&Refer=top",
    "hot": 135239
  },
  "这些OST一响2024画面感就来了": {
    "url": "https://s.weibo.com/weibo?q=%23%E8%BF%99%E4%BA%9BOST%E4%B8%80%E5%93%8D2024%E7%94%BB%E9%9D%A2%E6%84%9F%E5%B0%B1%E6%9D%A5%E4%BA%86%23&t=31&band_rank=42&Refer=top",
    "hot": 132298
  },
  "王者联动QQ飞车": {
    "url": "https://s.weibo.com/weibo?q=%23%E7%8E%8B%E8%80%85%E8%81%94%E5%8A%A8QQ%E9%A3%9E%E8%BD%A6%23&t=31&band_rank=48&Refer=top",
    "hot": 132030
  },
  "张凌赫自拍vs街拍": {
    "url": "https://s.weibo.com/weibo?q=%23%E5%BC%A0%E5%87%8C%E8%B5%AB%E8%87%AA%E6%8B%8Dvs%E8%A1%97%E6%8B%8D%23&t=31&band_rank=43&Refer=top",
    "hot": 129914
  },
  "乔任梁父亲首次回应巨额封口费一说": {
    "url": "https://s.weibo.com/weibo?q=%23%E4%B9%94%E4%BB%BB%E6%A2%81%E7%88%B6%E4%BA%B2%E9%A6%96%E6%AC%A1%E5%9B%9E%E5%BA%94%E5%B7%A8%E9%A2%9D%E5%B0%81%E5%8F%A3%E8%B4%B9%E4%B8%80%E8%AF%B4%23&t=31&band_rank=44&Refer=top",
    "hot": 129628
  },
  "华晨宇粉色永生花造型": {
    "url": "https://s.weibo.com/weibo?q=%E5%8D%8E%E6%99%A8%E5%AE%87%E7%B2%89%E8%89%B2%E6%B0%B8%E7%94%9F%E8%8A%B1%E9%80%A0%E5%9E%8B&t=31&band_rank=49&Refer=top",
    "hot": 128188
  },
  "因果报应21刀只是体力的极限": {
    "url": "https://s.weibo.com/weibo?q=%E5%9B%A0%E6%9E%9C%E6%8A%A5%E5%BA%9421%E5%88%80%E5%8F%AA%E6%98%AF%E4%BD%93%E5%8A%9B%E7%9A%84%E6%9E%81%E9%99%90&t=31&band_rank=45&Refer=top",
    "hot": 128063
  },
  "国考每一步都在淘汰人": {
    "url": "https://s.weibo.com/weibo?q=%23%E5%9B%BD%E8%80%83%E6%AF%8F%E4%B8%80%E6%AD%A5%E9%83%BD%E5%9C%A8%E6%B7%98%E6%B1%B0%E4%BA%BA%23&t=31&band_rank=50&Refer=top",
    "hot": 125636
  },
  "MMA颁奖典礼": {
    "url": "https://s.weibo.com/weibo?q=MMA%E9%A2%81%E5%A5%96%E5%85%B8%E7%A4%BC&t=31&band_rank=46&Refer=top",
    "hot": 121755
  },
  "王源粉丝买电影票像玩拼豆": {
    "url": "https://s.weibo.com/weibo?q=%E7%8E%8B%E6%BA%90%E7%B2%89%E4%B8%9D%E4%B9%B0%E7%94%B5%E5%BD%B1%E7%A5%A8%E5%83%8F%E7%8E%A9%E6%8B%BC%E8%B1%86&t=31&band_rank=47&Refer=top",
    "hot": 110138
  },
  "叶嘉莹遗体告别仪式": {
    "url": "https://s.weibo.com/weibo?q=%23%E5%8F%B6%E5%98%89%E8%8E%B9%E9%81%97%E4%BD%93%E5%91%8A%E5%88%AB%E4%BB%AA%E5%BC%8F%23&t=31&band_rank=48&Refer=top",
    "hot": 106490
  },
  "樊振东王励勤男双": {
    "url": "https://s.weibo.com/weibo?q=%23%E6%A8%8A%E6%8C%AF%E4%B8%9C%E7%8E%8B%E5%8A%B1%E5%8B%A4%E7%94%B7%E5%8F%8C%23&t=31&band_rank=49&Refer=top",
    "hot": 105143
  },
  "虞书欣她拍vs自拍": {
    "url": "https://s.weibo.com/weibo?q=%23%E8%99%9E%E4%B9%A6%E6%AC%A3%E5%A5%B9%E6%8B%8Dvs%E8%87%AA%E6%8B%8D%23&t=31&band_rank=50&Refer=top",
    "hot": 104943
  }
}