{
  "新华社出图": {
    "url": "https://s.weibo.com/weibo?q=%23%E6%96%B0%E5%8D%8E%E7%A4%BE%E5%87%BA%E5%9B%BE%23&t=31&band_rank=1&Refer=top",
    "hot": 6491617
  },
  "阅兵收视率": {
    "url": "https://s.weibo.com/weibo?q=%23%E9%98%85%E5%85%B5%E6%94%B6%E8%A7%86%E7%8E%87%23&t=31&band_rank=2&Refer=top",
    "hot": 2311498
  },
  "中国军队装备已经NextLevel": {
    "url": "https://s.weibo.com/weibo?q=%23%E4%B8%AD%E5%9B%BD%E5%86%9B%E9%98%9F%E8%A3%85%E5%A4%87%E5%B7%B2%E7%BB%8FNextLevel%23&t=31&band_rank=3&Refer=top",
    "hot": 1523638
  },
  "笨笨 你是军犬": {
    "url": "https://s.weibo.com/weibo?q=%E7%AC%A8%E7%AC%A8%20%E4%BD%A0%E6%98%AF%E5%86%9B%E7%8A%AC&t=31&band_rank=4&Refer=top",
    "hot": 1517326
  },
  "这几个无人机出来军事博主都沉默了": {
    "url": "https://s.weibo.com/weibo?q=%E8%BF%99%E5%87%A0%E4%B8%AA%E6%97%A0%E4%BA%BA%E6%9C%BA%E5%87%BA%E6%9D%A5%E5%86%9B%E4%BA%8B%E5%8D%9A%E4%B8%BB%E9%83%BD%E6%B2%89%E9%BB%98%E4%BA%86&t=31&band_rank=5&Refer=top",
    "hot": 1132659
  },
  "法新社出图": {
    "url": "https://s.weibo.com/weibo?q=%23%E6%B3%95%E6%96%B0%E7%A4%BE%E5%87%BA%E5%9B%BE%23&t=31&band_rank=6&Refer=top",
    "hot": 1128793
  },
  "九三盛大阅兵": {
    "url": "https://s.weibo.com/weibo?q=%23%E4%B9%9D%E4%B8%89%E7%9B%9B%E5%A4%A7%E9%98%85%E5%85%B5%23&t=31&band_rank=7&Refer=top",
    "hot": 1124343
  },
  "阅兵时五角大楼附近披萨订单激增": {
    "url": "https://s.weibo.com/weibo?q=%23%E9%98%85%E5%85%B5%E6%97%B6%E4%BA%94%E8%A7%92%E5%A4%A7%E6%A5%BC%E9%99%84%E8%BF%91%E6%8A%AB%E8%90%A8%E8%AE%A2%E5%8D%95%E6%BF%80%E5%A2%9E%23&t=31&band_rank=8&Refer=top",
    "hot": 888474
  },
  "郭帆 改剧本": {
    "url": "https://s.weibo.com/weibo?q=%E9%83%AD%E5%B8%86%20%E6%94%B9%E5%89%A7%E6%9C%AC&t=31&band_rank=9&Refer=top",
    "hot": 771564
  },
  "众多台湾网友观看了阅兵直播": {
    "url": "https://s.weibo.com/weibo?q=%23%E4%BC%97%E5%A4%9A%E5%8F%B0%E6%B9%BE%E7%BD%91%E5%8F%8B%E8%A7%82%E7%9C%8B%E4%BA%86%E9%98%85%E5%85%B5%E7%9B%B4%E6%92%AD%23&t=31&band_rank=10&Refer=top",
    "hot": 737683
  },
  "去现场观礼的明星": {
    "url": "https://s.weibo.com/weibo?q=%23%E5%8E%BB%E7%8E%B0%E5%9C%BA%E8%A7%82%E7%A4%BC%E7%9A%84%E6%98%8E%E6%98%9F%23&t=31&band_rank=11&Refer=top",
    "hot": 735706
  },
  "普京盛赞九三阅兵": {
    "url": "https://s.weibo.com/weibo?q=%23%E6%99%AE%E4%BA%AC%E7%9B%9B%E8%B5%9E%E4%B9%9D%E4%B8%89%E9%98%85%E5%85%B5%23&t=31&band_rank=12&Refer=top",
    "hot": 716034
  },
  "东风5C打击范围覆盖全球": {
    "url": "https://s.weibo.com/weibo?q=%23%E4%B8%9C%E9%A3%8E5C%E6%89%93%E5%87%BB%E8%8C%83%E5%9B%B4%E8%A6%86%E7%9B%96%E5%85%A8%E7%90%83%23&t=31&band_rank=13&Refer=top",
    "hot": 681030
  },
  "军事航天部队方队首次亮相": {
    "url": "https://s.weibo.com/weibo?q=%23%E5%86%9B%E4%BA%8B%E8%88%AA%E5%A4%A9%E9%83%A8%E9%98%9F%E6%96%B9%E9%98%9F%E9%A6%96%E6%AC%A1%E4%BA%AE%E7%9B%B8%23&t=31&band_rank=14&Refer=top",
    "hot": 678250
  },
  "东风61把大家给整不会了": {
    "url": "https://s.weibo.com/weibo?q=%E4%B8%9C%E9%A3%8E61%E6%8A%8A%E5%A4%A7%E5%AE%B6%E7%BB%99%E6%95%B4%E4%B8%8D%E4%BC%9A%E4%BA%86&t=31&band_rank=15&Refer=top",
    "hot": 528521
  },
  "阅兵飞机": {
    "url": "https://s.weibo.com/weibo?q=%E9%98%85%E5%85%B5%E9%A3%9E%E6%9C%BA&t=31&band_rank=16&Refer=top",
    "hot": 512618
  },
  "天安门上空这一幕令人震撼": {
    "url": "https://s.weibo.com/weibo?q=%23%E5%A4%A9%E5%AE%89%E9%97%A8%E4%B8%8A%E7%A9%BA%E8%BF%99%E4%B8%80%E5%B9%95%E4%BB%A4%E4%BA%BA%E9%9C%87%E6%92%BC%23&t=31&band_rank=17&Refer=top",
    "hot": 505041
  },
  "赖冠霖ins晒观礼照": {
    "url": "https://s.weibo.com/weibo?q=%23%E8%B5%96%E5%86%A0%E9%9C%96ins%E6%99%92%E8%A7%82%E7%A4%BC%E7%85%A7%23&t=31&band_rank=18&Refer=top",
    "hot": 483432
  },
  "外籍记者看阅兵后忍不住哭泣": {
    "url": "https://s.weibo.com/weibo?q=%23%E5%A4%96%E7%B1%8D%E8%AE%B0%E8%80%85%E7%9C%8B%E9%98%85%E5%85%B5%E5%90%8E%E5%BF%8D%E4%B8%8D%E4%BD%8F%E5%93%AD%E6%B3%A3%23&t=31&band_rank=19&Refer=top",
    "hot": 477879
  },
  "放飞和平鸽": {
    "url": "https://s.weibo.com/weibo?q=%23%E6%94%BE%E9%A3%9E%E5%92%8C%E5%B9%B3%E9%B8%BD%23&t=31&band_rank=20&Refer=top",
    "hot": 448895
  },
  "商家笑了俩小时才退款": {
    "url": "https://s.weibo.com/weibo?q=%E5%95%86%E5%AE%B6%E7%AC%91%E4%BA%86%E4%BF%A9%E5%B0%8F%E6%97%B6%E6%89%8D%E9%80%80%E6%AC%BE&t=31&band_rank=21&Refer=top",
    "hot": 432340
  },
  "受阅部队跑步登车画面被怒夸": {
    "url": "https://s.weibo.com/weibo?q=%23%E5%8F%97%E9%98%85%E9%83%A8%E9%98%9F%E8%B7%91%E6%AD%A5%E7%99%BB%E8%BD%A6%E7%94%BB%E9%9D%A2%E8%A2%AB%E6%80%92%E5%A4%B8%23&t=31&band_rank=22&Refer=top",
    "hot": 406029
  },
  "人民日报东风5C现场图": {
    "url": "https://s.weibo.com/weibo?q=%23%E4%BA%BA%E6%B0%91%E6%97%A5%E6%8A%A5%E4%B8%9C%E9%A3%8E5C%E7%8E%B0%E5%9C%BA%E5%9B%BE%23&t=31&band_rank=23&Refer=top",
    "hot": 390845
  },
  "你要的超燃阅兵壁纸来了": {
    "url": "https://s.weibo.com/weibo?q=%23%E4%BD%A0%E8%A6%81%E7%9A%84%E8%B6%85%E7%87%83%E9%98%85%E5%85%B5%E5%A3%81%E7%BA%B8%E6%9D%A5%E4%BA%86%23&t=31&band_rank=24&Refer=top",
    "hot": 367284
  },
  "国外网友被中国阅兵震惊": {
    "url": "https://s.weibo.com/weibo?q=%E5%9B%BD%E5%A4%96%E7%BD%91%E5%8F%8B%E8%A2%AB%E4%B8%AD%E5%9B%BD%E9%98%85%E5%85%B5%E9%9C%87%E6%83%8A&t=31&band_rank=25&Refer=top",
    "hot": 356281
  },
  "王楚钦穿北京大学校服": {
    "url": "https://s.weibo.com/weibo?q=%E7%8E%8B%E6%A5%9A%E9%92%A6%E7%A9%BF%E5%8C%97%E4%BA%AC%E5%A4%A7%E5%AD%A6%E6%A0%A1%E6%9C%8D&t=31&band_rank=26&Refer=top",
    "hot": 326062
  },
  "王楚钦开学": {
    "url": "https://s.weibo.com/weibo?q=%23%E7%8E%8B%E6%A5%9A%E9%92%A6%E5%BC%80%E5%AD%A6%23&t=31&band_rank=27&Refer=top",
    "hot": 302947
  },
  "多型特种飞机列装": {
    "url": "https://s.weibo.com/weibo?q=%23%E5%A4%9A%E5%9E%8B%E7%89%B9%E7%A7%8D%E9%A3%9E%E6%9C%BA%E5%88%97%E8%A3%85%23&t=31&band_rank=28&Refer=top",
    "hot": 296828
  },
  "水下兵器亮相阅兵": {
    "url": "https://s.weibo.com/weibo?q=%23%E6%B0%B4%E4%B8%8B%E5%85%B5%E5%99%A8%E4%BA%AE%E7%9B%B8%E9%98%85%E5%85%B5%23&t=31&band_rank=29&Refer=top",
    "hot": 293733
  },
  "肖思远烈士弟弟肖荣基参加阅兵活动": {
    "url": "https://s.weibo.com/weibo?q=%23%E8%82%96%E6%80%9D%E8%BF%9C%E7%83%88%E5%A3%AB%E5%BC%9F%E5%BC%9F%E8%82%96%E8%8D%A3%E5%9F%BA%E5%8F%82%E5%8A%A0%E9%98%85%E5%85%B5%E6%B4%BB%E5%8A%A8%23&t=31&band_rank=30&Refer=top",
    "hot": 266169
  },
  "99B坦克率先亮相": {
    "url": "https://s.weibo.com/weibo?q=%2399B%E5%9D%A6%E5%85%8B%E7%8E%87%E5%85%88%E4%BA%AE%E7%9B%B8%23&t=31&band_rank=31&Refer=top",
    "hot": 265101
  },
  "长剑1000导弹": {
    "url": "https://s.weibo.com/weibo?q=%23%E9%95%BF%E5%89%911000%E5%AF%BC%E5%BC%B9%23&t=31&band_rank=32&Refer=top",
    "hot": 262411
  },
  "新华社秒了": {
    "url": "https://s.weibo.com/weibo?q=%23%E6%96%B0%E5%8D%8E%E7%A4%BE%E7%A7%92%E4%BA%86%23&t=31&band_rank=33&Refer=top",
    "hot": 246935
  },
  "杜江预言家来了": {
    "url": "https://s.weibo.com/weibo?q=%23%E6%9D%9C%E6%B1%9F%E9%A2%84%E8%A8%80%E5%AE%B6%E6%9D%A5%E4%BA%86%23&t=31&band_rank=34&Refer=top",
    "hot": 242342
  },
  "云秀行": {
    "url": "https://s.weibo.com/weibo?q=%E4%BA%91%E7%A7%80%E8%A1%8C&t=31&band_rank=35&Refer=top",
    "hot": 235944
  },
  "好帅的女机长": {
    "url": "https://s.weibo.com/weibo?q=%E5%A5%BD%E5%B8%85%E7%9A%84%E5%A5%B3%E6%9C%BA%E9%95%BF&t=31&band_rank=36&Refer=top",
    "hot": 234902
  },
  "空着的1945检阅车": {
    "url": "https://s.weibo.com/weibo?q=%23%E7%A9%BA%E7%9D%80%E7%9A%841945%E6%A3%80%E9%98%85%E8%BD%A6%23&t=31&band_rank=37&Refer=top",
    "hot": 228782
  },
  "这盛世如您所愿": {
    "url": "https://s.weibo.com/weibo?q=%23%E8%BF%99%E7%9B%9B%E4%B8%96%E5%A6%82%E6%82%A8%E6%89%80%E6%84%BF%23&t=31&band_rank=38&Refer=top",
    "hot": 217353
  },
  "13个徒步方队完整视频": {
    "url": "https://s.weibo.com/weibo?q=%2313%E4%B8%AA%E5%BE%92%E6%AD%A5%E6%96%B9%E9%98%9F%E5%AE%8C%E6%95%B4%E8%A7%86%E9%A2%91%23&t=31&band_rank=39&Refer=top",
    "hot": 203978
  },
  "阅兵直播": {
    "url": "https://s.weibo.com/weibo?q=%E9%98%85%E5%85%B5%E7%9B%B4%E6%92%AD&t=31&band_rank=40&Refer=top",
    "hot": 198961
  },
  "阅兵结束一只和平鸽停在人群中间": {
    "url": "https://s.weibo.com/weibo?q=%23%E9%98%85%E5%85%B5%E7%BB%93%E6%9D%9F%E4%B8%80%E5%8F%AA%E5%92%8C%E5%B9%B3%E9%B8%BD%E5%81%9C%E5%9C%A8%E4%BA%BA%E7%BE%A4%E4%B8%AD%E9%97%B4%23&t=31&band_rank=41&Refer=top",
    "hot": 197023
  },
  "马龙陈梦合影": {
    "url": "https://s.weibo.com/weibo?q=%E9%A9%AC%E9%BE%99%E9%99%88%E6%A2%A6%E5%90%88%E5%BD%B1&t=31&band_rank=42&Refer=top",
    "hot": 193409
  },
  "运20 胖妞": {
    "url": "https://s.weibo.com/weibo?q=%E8%BF%9020%20%E8%83%96%E5%A6%9E&t=31&band_rank=43&Refer=top",
    "hot": 186738
  },
  "和平鸽参加阅兵全过程": {
    "url": "https://s.weibo.com/weibo?q=%E5%92%8C%E5%B9%B3%E9%B8%BD%E5%8F%82%E5%8A%A0%E9%98%85%E5%85%B5%E5%85%A8%E8%BF%87%E7%A8%8B&t=31&band_rank=44&Refer=top",
    "hot": 186364
  },
  "霍震霆与两儿子齐聚北京看九三阅兵": {
    "url": "https://s.weibo.com/weibo?q=%23%E9%9C%8D%E9%9C%87%E9%9C%86%E4%B8%8E%E4%B8%A4%E5%84%BF%E5%AD%90%E9%BD%90%E8%81%9A%E5%8C%97%E4%BA%AC%E7%9C%8B%E4%B9%9D%E4%B8%89%E9%98%85%E5%85%B5%23&t=31&band_rank=45&Refer=top",
    "hot": 184761
  },
  "我陆海空基战略核力量首次集中展示": {
    "url": "https://s.weibo.com/weibo?q=%23%E6%88%91%E9%99%86%E6%B5%B7%E7%A9%BA%E5%9F%BA%E6%88%98%E7%95%A5%E6%A0%B8%E5%8A%9B%E9%87%8F%E9%A6%96%E6%AC%A1%E9%9B%86%E4%B8%AD%E5%B1%95%E7%A4%BA%23&t=31&band_rank=46&Refer=top",
    "hot": 178461
  },
  "梨形身材是中了基因彩票": {
    "url": "https://s.weibo.com/weibo?q=%E6%A2%A8%E5%BD%A2%E8%BA%AB%E6%9D%90%E6%98%AF%E4%B8%AD%E4%BA%86%E5%9F%BA%E5%9B%A0%E5%BD%A9%E7%A5%A8&t=31&band_rank=47&Refer=top",
    "hot": 177857
  },
  "孙杨观看阅兵后发文": {
    "url": "https://s.weibo.com/weibo?q=%23%E5%AD%99%E6%9D%A8%E8%A7%82%E7%9C%8B%E9%98%85%E5%85%B5%E5%90%8E%E5%8F%91%E6%96%87%23&t=31&band_rank=48&Refer=top",
    "hot": 164136
  },
  "马龙观看阅兵震撼又幸福": {
    "url": "https://s.weibo.com/weibo?q=%E9%A9%AC%E9%BE%99%E8%A7%82%E7%9C%8B%E9%98%85%E5%85%B5%E9%9C%87%E6%92%BC%E5%8F%88%E5%B9%B8%E7%A6%8F&t=31&band_rank=49&Refer=top",
    "hot": 155531
  },
  "陈梦说看到方队瞬间起鸡皮疙瘩": {
    "url": "https://s.weibo.com/weibo?q=%23%E9%99%88%E6%A2%A6%E8%AF%B4%E7%9C%8B%E5%88%B0%E6%96%B9%E9%98%9F%E7%9E%AC%E9%97%B4%E8%B5%B7%E9%B8%A1%E7%9A%AE%E7%96%99%E7%98%A9%23&t=31&band_rank=50&Refer=top",
    "hot": 153509
  }
}